dagster_swarm/__init__.py
dagster_swarm/py.typed
dagster_swarm/run_launchers.py
dagster_swarm-0.0.1.dist-info/METADATA
dagster_swarm-0.0.1.dist-info/WHEEL
dagster_swarm-0.0.1.dist-info/licenses/LICENSE
dagster_swarm-0.0.1.dist-info/RECORD
